propmtshield/__init__.py
promptshield-0.1.0.dist-info/LICENSE
promptshield-0.1.0.dist-info/METADATA
promptshield-0.1.0.dist-info/WHEEL
promptshield-0.1.0.dist-info/top_level.txt
promptshield-0.1.0.dist-info/RECORD
