Metadata-Version: 2.1
Name: promptshield
Version: 0.1.0
Summary: An empty PyPI package
Home-page: https://github.com/yourusername/my_empty_package
Author: Your Name
Author-email: your.email@example.com
Classifier: Programming Language :: Python :: 3
Classifier: License :: OSI Approved :: MIT License
Classifier: Operating System :: OS Independent
Requires-Python: >=3.6
License-File: LICENSE
